aiorpcx/__init__.py
aiorpcx_spesmilo-0.dist-info/LICENSE
aiorpcx_spesmilo-0.dist-info/METADATA
aiorpcx_spesmilo-0.dist-info/WHEEL
aiorpcx_spesmilo-0.dist-info/top_level.txt
aiorpcx_spesmilo-0.dist-info/RECORD
