Metadata-Version: 2.1
Name: aiorpcx-spesmilo
Version: 0
Summary: Generic async RPC implementation, including JSON-RPC
Home-page: https://github.com/spesmilo/aiorpcx
Author: Electrum developers
Author-email: electrumdev@gmail.com
License: MIT Licence
Platform: UNKNOWN
Classifier: Development Status :: 1 - Planning
Classifier: License :: OSI Approved :: MIT License
Classifier: Operating System :: OS Independent
Classifier: Programming Language :: Python :: 3
